vlm/__init__.py
vlm/connectors/__init__.py
vlm/connectors/base.py
vlm/connectors/onvif.py
vlm/connectors/rtsp.py
vlm/connectors/udp.py
vlm/connectors/webrtc.py
vlm/core/__init__.py
vlm/core/config.py
vlm/core/pipeline.py
vlm/core/types.py
vlm/preprocessors/__init__.py
vlm/preprocessors/base.py
vlm/preprocessors/detector/__init__.py
vlm/preprocessors/detector/caching.py
vlm/preprocessors/detector/core.py
vlm/preprocessors/detector/events.py
vlm/preprocessors/detector/motion_tracker.py
vlm/preprocessors/detector/tracking.py
vlm/providers/__init__.py
vlm/providers/base.py
vlm/providers/gemini.py
vlm/providers/qwen.py
vlm_sdk-0.0.3.dist-info/licenses/LICENSE
vlm_sdk-0.0.3.dist-info/METADATA
vlm_sdk-0.0.3.dist-info/WHEEL
vlm_sdk-0.0.3.dist-info/top_level.txt
vlm_sdk-0.0.3.dist-info/RECORD
