Metadata-Version: 2.4
Name: vlm-sdk
Version: 0.0.3
Summary: VLMS - Video Intelligence SDK with event-based processing
Author-email: Rishabh <rishabh@observee.com>
License: Apache-2.0
Keywords: video,ai,vlm,gemini,vision,rtdetr,detection,rtsp,onvif
Classifier: Development Status :: 3 - Alpha
Classifier: Intended Audience :: Developers
Classifier: License :: OSI Approved :: Apache Software License
Classifier: Programming Language :: Python :: 3.10
Classifier: Programming Language :: Python :: 3.11
Classifier: Programming Language :: Python :: 3.12
Requires-Python: >=3.10
License-File: LICENSE
Requires-Dist: opencv-python>=4.10.0
Requires-Dist: numpy>=1.26.0
Requires-Dist: google-genai>=0.8.0
Requires-Dist: torch>=2.1.0
Requires-Dist: transformers>=4.36.0
Requires-Dist: pillow>=10.0.0
Requires-Dist: onvif-zeep>=0.2.12
Requires-Dist: aiortc>=1.6.0
Requires-Dist: av>=11.0.0
Requires-Dist: openai>=1.0.0
Provides-Extra: dev
Requires-Dist: pytest>=7.0.0; extra == "dev"
Requires-Dist: black>=23.0.0; extra == "dev"
Requires-Dist: ruff>=0.1.0; extra == "dev"
Dynamic: license-file
